Workbook

Sheet Summary
A1: Renovation Cost Estimate - by Room
A2: Brattleboro, VT - Mid-range finish tier - Prepared June 2026
A3: Planning estimate from listing photos + renovation renders. Material (COGS) lines link to current retail references; labor reflects VT trade rates. Verify with contractor bids.
A5: Room | B5: COGS (materials) | C5: Labor | D5: Room Total
A6: Kitchen | B6: =Kitchen!E17 -> 10828 | C6: =Kitchen!F17 -> 7556 | D6: =B6+C6 -> 18384
A7: Living / Great Room | B7: ='Living - Great Room'!E11 -> 2180 | C7: ='Living - Great Room'!F11 -> 5860 | D7: =B7+C7 -> 8040
A8: Dining Room | B8: ='Dining Room'!E9 -> 1780 | C8: ='Dining Room'!F9 -> 2510 | D8: =B8+C8 -> 4290
A9: Entry / Foyer & Stairs | B9: ='Entry - Foyer & Stairs'!E10 -> 2860 | C9: ='Entry - Foyer & Stairs'!F10 -> 5210 | D9: =B9+C9 -> 8070
A10: Bathroom - Main (1st flr) | B10: ='Bathroom - Main (1st flr)'!E16 -> 2830 | C10: ='Bathroom - Main (1st flr)'!F16 -> 4575 | D10: =B10+C10 -> 7405
A11: Bathroom - Upstairs (clawfoot) | B11: ='Bathroom - Upstairs (clawfoot)'!E15 -> 5610 | C11: ='Bathroom - Upstairs (clawfoot)'!F15 -> 6005 | D11: =B11+C11 -> 11615
A12: Bedroom 1 - Kids Loft | B12: ='Bedroom 1 - Kids Loft'!E12 -> 3430 | C12: ='Bedroom 1 - Kids Loft'!F12 -> 5680 | D12: =B12+C12 -> 9110
A13: Bedroom 2 - Pine | B13: ='Bedroom 2 - Pine'!E11 -> 3010 | C13: ='Bedroom 2 - Pine'!F11 -> 5030 | D13: =B13+C13 -> 8040
A14: General / Whole-House | B14: ='General - Whole-House'!E11 -> 1540 | C14: ='General - Whole-House'!F11 -> 7400 | D14: =B14+C14 -> 8940
A15: SUBTOTAL (hard costs) | B15: =SUM(B6:B14) -> 34068 | C15: =SUM(C6:C14) -> 49826 | D15: =SUM(D6:D14) -> 83894
A16: GC overhead & profit (15% of subtotal) | C16: soft cost | D16: =0.15*D15 -> 12584.1
A17: Contingency (12% of subtotal + OH&P) | D17: =0.12*(D15+D16) -> 11577.372
A18: ESTIMATED PROJECT TOTAL | D18: =D15+D16+D17 -> 108055.47
A20: Hard-cost split:
A21: Total materials (COGS) | D21: =B15 -> 34068
A22: Total labor | D22: =C15 -> 49826

Sheet Assumptions & Notes
A1: Assumptions & Methodology
A3: Finish tier: Mid-range - quality stock/semi-custom materials with professional contractor labor, matching the renovation renders (butcher block, tile, mini-split heat pumps, refinished wood floors, pine paneling).
A4: Location: Brattleboro, Vermont. Labor reflects current VT trade wage rates (electricians ~$33-35/hr, plumbers ~$32-38/hr base; loaded contractor billing rates run materially higher and are embedded in the labor figures).
A6: Square-footage assumptions (estimated from photos - confirm with measurements):
A7: Kitchen ~180 sf / Living-Great Room ~320 sf / Dining ~180 sf / Entry-Foyer ~120 sf
A8: Main bath ~70 sf / Upstairs bath ~90 sf / Bedroom 1 ~180 sf / Bedroom 2 ~180 sf / Ceilings for popcorn removal ~1,100 sf
A10: Scope captured from renders: full kitchen gut (semi-custom cabinets, maple butcher block, fireclay farmhouse sink, tile backsplash, open shelving, peninsula, new stainless appliances); two bathroom remodels (main bath - terracotta floor, tiled tub surround, pine wainscot, new vanity; upstairs bath - cast-iron clawfoot tub, hex terracotta floor, brass fixtures, wood vanity); pine tongue-and-groove paneling in both upstairs bedrooms; refinished wide-plank wood floors throughout; slate-tiled entry with rebuilt staircase; cleaned/stained exposed beams + recessed lighting in the great room; three mini-split heat pump heads; whole-house popcorn ceiling removal and repaint.
A12: COGS = cost of goods / materials. Every material line links to a current retail reference (mostly Home Depot) so prices can be re-checked. Labor totals are a separate column on each line and roll up separately on the Summary tab.
A13: GC overhead & profit (15%) and contingency (12%) are added on the Summary tab. For an older Vermont home, budget a 10-20% contingency for hidden conditions behind walls.
A15: This is a planning-level estimate, NOT a contractor bid. Actual costs vary with material selections, hidden conditions (wiring/knob-and-tube, plumbing, insulation, water damage, structural), permit requirements, and contractor availability. Get 2-3 local bids before committing a budget.

Sheet Kitchen
A1: Kitchen
A2: Mid-range finish tier - Brattleboro, VT - planning estimate
A4: Item / Scope | B4: Qty | C4: Unit | D4: COGS $/unit | E4: COGS Total | F4: Labor Total | G4: Material Reference (link)
A5: Demo existing kitchen (cabinets, counters, backsplash) | B5: 1 | C5: ls | D5: 0 | E5: =B5*D5 -> 0 | F5: =B5*800 -> 800 | G5: ZipRecruiter – VT Plumber Rate
A6: Semi-custom base & wall cabinets (shaker, natural) | B6: 22 | C6: lin ft | D6: 200 | E6: =B6*D6 -> 4400 | F6: =B6*100 -> 2200 | G6: Home Depot – Kitchen Cabinets
A7: Open wood shelving + brackets | B7: 6 | C7: shelf | D7: 60 | E7: =B7*D7 -> 360 | F7: =B7*40 -> 240 | G7: Home Depot – Dimensional Lumber & Trim
A8: Butcher block countertop (maple) | B8: 40 | C8: sq ft | D8: 45 | E8: =B8*D8 -> 1800 | F8: =B8*25 -> 1000 | G8: Home Depot – Maple Butcher Block
A9: Fireclay farmhouse apron sink, 30 in. | B9: 1 | C9: ea | D9: 260 | E9: =B9*D9 -> 260 | F9: =B9*150 -> 150 | G9: Home Depot – HOROW 30in Fireclay Farmhouse Sink
A10: Pull-down kitchen faucet | B10: 1 | C10: ea | D10: 220 | E10: =B10*D10 -> 220 | F10: =B10*120 -> 120 | G10: Home Depot – Kitchen Faucets
A11: Tile backsplash (glazed ceramic / zellige look) | B11: 32 | C11: sq ft | D11: 9 | E11: =B11*D11 -> 288 | F11: =B11*13 -> 416 | G11: Home Depot – Ceramic Wall Tile
A12: Stainless appliance package (range, dishwasher, fridge) | B12: 1 | C12: set | D12: 2600 | E12: =B12*D12 -> 2600 | F12: =B12*250 -> 250 | G12: Home Depot – SS Electric Appliance Package
A13: Track + flush-mount lighting, recessed cans | B13: 1 | C13: ls | D13: 450 | E13: =B13*D13 -> 450 | F13: =B13*700 -> 700 | G13: Home Depot – Lighting Fixtures
A14: Plumbing reconnect (sink + dishwasher) | B14: 1 | C14: ls | D14: 0 | E14: =B14*D14 -> 0 | F14: =B14*600 -> 600 | G14: ZipRecruiter – VT Plumber Rate
A15: Refinish wood floor | B15: 180 | C15: sq ft | D15: 1.5 | E15: =B15*D15 -> 270 | F15: =B15*3.5 -> 630 | G15: Angi – Hardwood Refinishing Cost
A16: Paint walls & ceiling | B16: 180 | C16: sq ft | D16: 1 | E16: =B16*D16 -> 180 | F16: =B16*2.5 -> 450 | G16: Home Depot – Interior Paint
A17: ROOM SUBTOTAL | E17: =SUM(E5:E16) -> 10828 | F17: =SUM(F5:F16) -> 7556
A18: ROOM TOTAL (COGS + Labor) | E18: =E17+F17 -> 18384

Sheet Living - Great Room
A1: Living / Great Room
A2: Mid-range finish tier - Brattleboro, VT - planning estimate
A4: Item / Scope | B4: Qty | C4: Unit | D4: COGS $/unit | E4: COGS Total | F4: Labor Total | G4: Material Reference (link)
A5: Refinish wide-plank pine floor | B5: 320 | C5: sq ft | D5: 1.5 | E5: =B5*D5 -> 480 | F5: =B5*4 -> 1280 | G5: Angi – Hardwood Refinishing Cost
A6: Clean & stain exposed ceiling beams | B6: 1 | C6: ls | D6: 120 | E6: =B6*D6 -> 120 | F6: =B6*600 -> 600 | G6: Home Depot – Dimensional Lumber & Trim
A7: Recessed LED cans (retrofit) | B7: 6 | C7: ea | D7: 35 | E7: =B7*D7 -> 210 | F7: =B7*130 -> 780 | G7: Angi – Recessed Lighting Cost
A8: Mini-split heat pump head (12k BTU) + install | B8: 1 | C8: ea | D8: 750 | E8: =B8*D8 -> 750 | F8: =B8*2000 -> 2000 | G8: Home Depot – Pioneer 12k BTU Mini-Split Heat Pump
A9: Reset wood stove + new stovepipe section | B9: 1 | C9: ls | D9: 300 | E9: =B9*D9 -> 300 | F9: =B9*400 -> 400 | G9: Home Depot – Stove Pipe
A10: Paint walls & ceiling | B10: 320 | C10: sq ft | D10: 1 | E10: =B10*D10 -> 320 | F10: =B10*2.5 -> 800 | G10: Home Depot – Interior Paint
A11: ROOM SUBTOTAL | E11: =SUM(E5:E10) -> 2180 | F11: =SUM(F5:F10) -> 5860
A12: ROOM TOTAL (COGS + Labor) | E12: =E11+F11 -> 8040

Sheet Dining Room
A1: Dining Room
A2: Mid-range finish tier - Brattleboro, VT - planning estimate
A4: Item / Scope | B4: Qty | C4: Unit | D4: COGS $/unit | E4: COGS Total | F4: Labor Total | G4: Material Reference (link)
A5: Pine tongue & groove wall paneling | B5: 360 | C5: sq ft | D5: 3 | E5: =B5*D5 -> 1080 | F5: =B5*3 -> 1080 | G5: Home Depot – Pine Tongue & Groove Paneling
A6: Refinish wood floor | B6: 180 | C6: sq ft | D6: 1.5 | E6: =B6*D6 -> 270 | F6: =B6*4 -> 720 | G6: Angi – Hardwood Refinishing Cost
A7: Window casing/trim (pine) + curtain rod | B7: 1 | C7: ls | D7: 250 | E7: =B7*D7 -> 250 | F7: =B7*350 -> 350 | G7: Home Depot – Dimensional Lumber & Trim
A8: Paint ceiling | B8: 180 | C8: sq ft | D8: 1 | E8: =B8*D8 -> 180 | F8: =B8*2 -> 360 | G8: Home Depot – Interior Paint
A9: ROOM SUBTOTAL | E9: =SUM(E5:E8) -> 1780 | F9: =SUM(F5:F8) -> 2510
A10: ROOM TOTAL (COGS + Labor) | E10: =E9+F9 -> 4290

Sheet Entry - Foyer & Stairs
A1: Entry / Foyer & Stairs
A2: Mid-range finish tier - Brattleboro, VT - planning estimate
A4: Item / Scope | B4: Qty | C4: Unit | D4: COGS $/unit | E4: COGS Total | F4: Labor Total | G4: Material Reference (link)
A5: Slate tile floor (material + install) | B5: 120 | C5: sq ft | D5: 6 | E5: =B5*D5 -> 720 | F5: =B5*10 -> 1200 | G5: Home Depot – Slate Floor Tile
A6: Rebuilt wood staircase + railing | B6: 1 | C6: ls | D6: 1800 | E6: =B6*D6 -> 1800 | F6: =B6*3200 -> 3200 | G6: Home Depot – Dimensional Lumber & Trim
A7: Recessed LED cans (retrofit) | B7: 2 | C7: ea | D7: 35 | E7: =B7*D7 -> 70 | F7: =B7*130 -> 260 | G7: Angi – Recessed Lighting Cost
A8: Sliding-door trim refresh | B8: 1 | C8: ls | D8: 150 | E8: =B8*D8 -> 150 | F8: =B8*250 -> 250 | G8: Home Depot – Dimensional Lumber & Trim
A9: Paint walls & ceiling | B9: 120 | C9: sq ft | D9: 1 | E9: =B9*D9 -> 120 | F9: =B9*2.5 -> 300 | G9: Home Depot – Interior Paint
A10: ROOM SUBTOTAL | E10: =SUM(E5:E9) -> 2860 | F10: =SUM(F5:F9) -> 5210
A11: ROOM TOTAL (COGS + Labor) | E11: =E10+F10 -> 8070

Sheet Bathroom - Main (1st flr)
A1: Bathroom - Main (1st flr)
A2: Mid-range finish tier - Brattleboro, VT - planning estimate
A4: Item / Scope | B4: Qty | C4: Unit | D4: COGS $/unit | E4: COGS Total | F4: Labor Total | G4: Material Reference (link)
A5: Demo + backer board / subfloor prep | B5: 1 | C5: ls | D5: 200 | E5: =B5*D5 -> 200 | F5: =B5*700 -> 700 | G5: ZipRecruiter – VT Plumber Rate
A6: Terracotta / saltillo floor tile | B6: 70 | C6: sq ft | D6: 6 | E6: =B6*D6 -> 420 | F6: =B6*10 -> 700 | G6: Home Depot – Saltillo / Terracotta Tile
A7: Reglaze existing alcove tub | B7: 1 | C7: ea | D7: 0 | E7: =B7*D7 -> 0 | F7: =B7*500 -> 500 | G7: ZipRecruiter – VT Plumber Rate
A8: Tile tub surround | B8: 60 | C8: sq ft | D8: 8 | E8: =B8*D8 -> 480 | F8: =B8*13 -> 780 | G8: Home Depot – Ceramic Wall Tile
A9: Pine wainscoting | B9: 80 | C9: sq ft | D9: 3 | E9: =B9*D9 -> 240 | F9: =B9*3 -> 240 | G9: Home Depot – Pine Tongue & Groove Paneling
A10: Vanity w/ top, 36 in. | B10: 1 | C10: ea | D10: 550 | E10: =B10*D10 -> 550 | F10: =B10*200 -> 200 | G10: Home Depot – Bathroom Vanities w/ Tops
A11: Toilet | B11: 1 | C11: ea | D11: 220 | E11: =B11*D11 -> 220 | F11: =B11*180 -> 180 | G11: Home Depot – Toilets
A12: Tub/shower valve + faucet trim (brass) | B12: 1 | C12: set | D12: 450 | E12: =B12*D12 -> 450 | F12: =B12*350 -> 350 | G12: Home Depot – Bathroom / Shower Faucets
A13: Vanity + flush-mount lighting | B13: 1 | C13: ls | D13: 200 | E13: =B13*D13 -> 200 | F13: =B13*250 -> 250 | G13: Home Depot – Lighting Fixtures
A14: Plumbing rough adjustments | B14: 1 | C14: ls | D14: 0 | E14: =B14*D14 -> 0 | F14: =B14*500 -> 500 | G14: ZipRecruiter – VT Plumber Rate
A15: Paint | B15: 70 | C15: sq ft | D15: 1 | E15: =B15*D15 -> 70 | F15: =B15*2.5 -> 175 | G15: Home Depot – Interior Paint
A16: ROOM SUBTOTAL | E16: =SUM(E5:E15) -> 2830 | F16: =SUM(F5:F15) -> 4575
A17: ROOM TOTAL (COGS + Labor) | E17: =E16+F16 -> 7405

Sheet Bathroom - Upstairs (clawfoot)
A1: Bathroom - Upstairs (clawfoot)
A2: Mid-range finish tier - Brattleboro, VT - planning estimate
A4: Item / Scope | B4: Qty | C4: Unit | D4: COGS $/unit | E4: COGS Total | F4: Labor Total | G4: Material Reference (link)
A5: Demo + subfloor build-up (exposed subfloor) | B5: 1 | C5: ls | D5: 350 | E5: =B5*D5 -> 350 | F5: =B5*900 -> 900 | G5: ZipRecruiter – VT Plumber Rate
A6: Hex terracotta floor tile | B6: 90 | C6: sq ft | D6: 7 | E6: =B6*D6 -> 630 | F6: =B6*11 -> 990 | G6: Home Depot – Saltillo / Terracotta Tile
A7: Cast-iron clawfoot soaking tub | B7: 1 | C7: ea | D7: 1700 | E7: =B7*D7 -> 1700 | F7: =B7*500 -> 500 | G7: Home Depot – Cast Iron Clawfoot Tubs
A8: Floor-mount tub filler (brass) | B8: 1 | C8: ea | D8: 650 | E8: =B8*D8 -> 650 | F8: =B8*450 -> 450 | G8: Home Depot – Freestanding Tub Faucets
A9: Tile wainscot + tub wall | B9: 70 | C9: sq ft | D9: 6 | E9: =B9*D9 -> 420 | F9: =B9*13 -> 910 | G9: Home Depot – Ceramic Wall Tile
A10: Wood vanity w/ top + sink + faucet | B10: 1 | C10: ls | D10: 900 | E10: =B10*D10 -> 900 | F10: =B10*350 -> 350 | G10: Home Depot – Bathroom Vanities w/ Tops
A11: Toilet | B11: 1 | C11: ea | D11: 220 | E11: =B11*D11 -> 220 | F11: =B11*180 -> 180 | G11: Home Depot – Toilets
A12: Brass wall sconces + skylight trim | B12: 1 | C12: ls | D12: 350 | E12: =B12*D12 -> 350 | F12: =B12*300 -> 300 | G12: Home Depot – Lighting Fixtures
A13: Plumbing rough (relocate for clawfoot + filler) | B13: 1 | C13: ls | D13: 300 | E13: =B13*D13 -> 300 | F13: =B13*1200 -> 1200 | G13: ZipRecruiter – VT Plumber Rate
A14: Paint | B14: 90 | C14: sq ft | D14: 1 | E14: =B14*D14 -> 90 | F14: =B14*2.5 -> 225 | G14: Home Depot – Interior Paint
A15: ROOM SUBTOTAL | E15: =SUM(E5:E14) -> 5610 | F15: =SUM(F5:F14) -> 6005
A16: ROOM TOTAL (COGS + Labor) | E16: =E15+F15 -> 11615

Sheet Bedroom 1 - Kids Loft
A1: Bedroom 1 - Kids Loft
A2: Mid-range finish tier - Brattleboro, VT - planning estimate
A4: Item / Scope | B4: Qty | C4: Unit | D4: COGS $/unit | E4: COGS Total | F4: Labor Total | G4: Material Reference (link)
A5: Pine T&G paneling (walls + ceiling) | B5: 520 | C5: sq ft | D5: 3 | E5: =B5*D5 -> 1560 | F5: =B5*3 -> 1560 | G5: Home Depot – Pine Tongue & Groove Paneling
A6: Refinish pine floor | B6: 180 | C6: sq ft | D6: 1.5 | E6: =B6*D6 -> 270 | F6: =B6*4 -> 720 | G6: Angi – Hardwood Refinishing Cost
A7: Loft refresh: ladder, rail, storage cubbies | B7: 1 | C7: ls | D7: 400 | E7: =B7*D7 -> 400 | F7: =B7*700 -> 700 | G7: Home Depot – Dimensional Lumber & Trim
A8: Mini-split heat pump head (12k BTU) + install | B8: 1 | C8: ea | D8: 750 | E8: =B8*D8 -> 750 | F8: =B8*2000 -> 2000 | G8: Home Depot – Pioneer 12k BTU Mini-Split Heat Pump
A9: Reseal / trim skylight | B9: 1 | C9: ea | D9: 100 | E9: =B9*D9 -> 100 | F9: =B9*200 -> 200 | G9: Home Depot – Dimensional Lumber & Trim
A10: Lighting + added outlets | B10: 1 | C10: ls | D10: 200 | E10: =B10*D10 -> 200 | F10: =B10*350 -> 350 | G10: Home Depot – Lighting Fixtures
A11: Closet door (pine) refit | B11: 1 | C11: ea | D11: 150 | E11: =B11*D11 -> 150 | F11: =B11*150 -> 150 | G11: Home Depot – Dimensional Lumber & Trim
A12: ROOM SUBTOTAL | E12: =SUM(E5:E11) -> 3430 | F12: =SUM(F5:F11) -> 5680
A13: ROOM TOTAL (COGS + Labor) | E13: =E12+F12 -> 9110

Sheet Bedroom 2 - Pine
A1: Bedroom 2 - Pine
A2: Mid-range finish tier - Brattleboro, VT - planning estimate
A4: Item / Scope | B4: Qty | C4: Unit | D4: COGS $/unit | E4: COGS Total | F4: Labor Total | G4: Material Reference (link)
A5: Pine T&G paneling (walls + ceiling) | B5: 520 | C5: sq ft | D5: 3 | E5: =B5*D5 -> 1560 | F5: =B5*3 -> 1560 | G5: Home Depot – Pine Tongue & Groove Paneling
A6: Refinish pine floor | B6: 180 | C6: sq ft | D6: 1.5 | E6: =B6*D6 -> 270 | F6: =B6*4 -> 720 | G6: Angi – Hardwood Refinishing Cost
A7: Mini-split heat pump head (12k BTU) + install | B7: 1 | C7: ea | D7: 750 | E7: =B7*D7 -> 750 | F7: =B7*2000 -> 2000 | G7: Home Depot – Pioneer 12k BTU Mini-Split Heat Pump
A8: Reseal / trim skylight | B8: 1 | C8: ea | D8: 100 | E8: =B8*D8 -> 100 | F8: =B8*200 -> 200 | G8: Home Depot – Dimensional Lumber & Trim
A9: Lighting + added outlets | B9: 1 | C9: ls | D9: 180 | E9: =B9*D9 -> 180 | F9: =B9*300 -> 300 | G9: Home Depot – Lighting Fixtures
A10: Window casing/trim (pine) | B10: 1 | C10: ls | D10: 150 | E10: =B10*D10 -> 150 | F10: =B10*250 -> 250 | G10: Home Depot – Dimensional Lumber & Trim
A11: ROOM SUBTOTAL | E11: =SUM(E5:E10) -> 3010 | F11: =SUM(F5:F10) -> 5030
A12: ROOM TOTAL (COGS + Labor) | E12: =E11+F11 -> 8040

Sheet General - Whole-House
A1: General / Whole-House
A2: Mid-range finish tier - Brattleboro, VT - planning estimate
A4: Item / Scope | B4: Qty | C4: Unit | D4: COGS $/unit | E4: COGS Total | F4: Labor Total | G4: Material Reference (link)
A5: Building permits & fees (Town of Brattleboro) | B5: 1 | C5: ls | D5: 0 | E5: =B5*D5 -> 0 | F5: =B5*900 -> 900 | G5: Town of Brattleboro – Permits
A6: Demolition & debris haul (3 dumpsters) | B6: 1 | C6: ls | D6: 0 | E6: =B6*D6 -> 0 | F6: =B6*2100 -> 2100 | G6: Angi – Popcorn Ceiling Removal Cost
A7: Electrical panel / circuit upgrades | B7: 1 | C7: ls | D7: 500 | E7: =B7*D7 -> 500 | F7: =B7*1500 -> 1500 | G7: ZipRecruiter – VT Electrician Rate
A8: Popcorn ceiling removal & skim coat | B8: 1100 | C8: sq ft | D8: 0.4 | E8: =B8*D8 -> 440 | F8: =B8*2 -> 2200 | G8: Angi – Popcorn Ceiling Removal Cost
A9: Misc fasteners, adhesives, consumables | B9: 1 | C9: ls | D9: 600 | E9: =B9*D9 -> 600 | F9: =B9*0 -> 0 | G9: Home Depot – Dimensional Lumber & Trim
A10: Final cleaning | B10: 1 | C10: ls | D10: 0 | E10: =B10*D10 -> 0 | F10: =B10*700 -> 700 | G10: Town of Brattleboro – Permits
A11: ROOM SUBTOTAL | E11: =SUM(E5:E10) -> 1540 | F11: =SUM(F5:F10) -> 7400
A12: ROOM TOTAL (COGS + Labor) | E12: =E11+F11 -> 8940
